laakhay/data/__init__.py
laakhay/data/clients/__init__.py
laakhay/data/clients/base_feed.py
laakhay/data/clients/liquidation_feed.py
laakhay/data/clients/ohlcv_feed.py
laakhay/data/clients/open_interest_feed.py
laakhay/data/core/__init__.py
laakhay/data/core/api.py
laakhay/data/core/base.py
laakhay/data/core/capabilities.py
laakhay/data/core/capability_service.py
laakhay/data/core/enums.py
laakhay/data/core/exceptions.py
laakhay/data/core/registry.py
laakhay/data/core/relay.py
laakhay/data/core/request.py
laakhay/data/core/router.py
laakhay/data/core/urm.py
laakhay/data/io/__init__.py
laakhay/data/io/rest/__init__.py
laakhay/data/io/rest/http.py
laakhay/data/io/rest/provider.py
laakhay/data/io/rest/runner.py
laakhay/data/io/rest/transport.py
laakhay/data/io/ws/__init__.py
laakhay/data/io/ws/client.py
laakhay/data/io/ws/provider.py
laakhay/data/io/ws/runner.py
laakhay/data/io/ws/transport.py
laakhay/data/models/__init__.py
laakhay/data/models/bar.py
laakhay/data/models/events.py
laakhay/data/models/funding_rate.py
laakhay/data/models/liquidation.py
laakhay/data/models/mark_price.py
laakhay/data/models/ohlcv.py
laakhay/data/models/open_interest.py
laakhay/data/models/order_book.py
laakhay/data/models/series_meta.py
laakhay/data/models/streaming_bar.py
laakhay/data/models/symbol.py
laakhay/data/models/trade.py
laakhay/data/providers/__init__.py
laakhay/data/providers/binance/__init__.py
laakhay/data/providers/binance/constants.py
laakhay/data/providers/binance/provider.py
laakhay/data/providers/binance/urm.py
laakhay/data/providers/binance/rest/adapters.py
laakhay/data/providers/binance/rest/endpoints.py
laakhay/data/providers/binance/rest/provider.py
laakhay/data/providers/binance/ws/adapters.py
laakhay/data/providers/binance/ws/endpoints.py
laakhay/data/providers/binance/ws/provider.py
laakhay/data/providers/bybit/__init__.py
laakhay/data/providers/bybit/constants.py
laakhay/data/providers/bybit/provider.py
laakhay/data/providers/bybit/urm.py
laakhay_data-0.2.5.dist-info/METADATA
laakhay_data-0.2.5.dist-info/WHEEL
laakhay_data-0.2.5.dist-info/licenses/LICENSE
laakhay_data-0.2.5.dist-info/RECORD
