Metadata-Version: 2.4
Name: laakhay-data
Version: 0.2.5
Summary: Data infrastructure built with ♥︎ by Laakhay
Project-URL: Homepage, https://laakhay.com
Author-email: Laakhay Corporation <laakhay.corp@gmail.com>
License-Expression: MIT
License-File: LICENSE
Keywords: finance,market-data,trading
Classifier: Development Status :: 3 - Alpha
Classifier: Intended Audience :: Developers
Classifier: Intended Audience :: Financial and Insurance Industry
Classifier: Programming Language :: Python :: 3.12
Classifier: Programming Language :: Python :: 3.13
Classifier: Topic :: Office/Business :: Financial
Requires-Python: >=3.12
Requires-Dist: aiohttp>=3.8
Requires-Dist: pydantic>=2.0
Requires-Dist: websockets>=10
Provides-Extra: dev
Requires-Dist: build>=1.0; extra == 'dev'
Requires-Dist: mypy>=1.0.0; extra == 'dev'
Requires-Dist: pytest-asyncio>=0.24.0; extra == 'dev'
Requires-Dist: pytest-cov>=4.0.0; extra == 'dev'
Requires-Dist: pytest>=8.0; extra == 'dev'
Requires-Dist: ruff>=0.4; extra == 'dev'
Requires-Dist: twine>=5.0; extra == 'dev'
